nebula/__init__.py
nebula/async_client.py
nebula/client.py
nebula/exceptions.py
nebula/models.py
nebula_client-2.1.15.dist-info/METADATA
nebula_client-2.1.15.dist-info/WHEEL
nebula_client-2.1.15.dist-info/top_level.txt
nebula_client-2.1.15.dist-info/RECORD
