Metadata-Version: 2.4
Name: nebula-client
Version: 2.1.15
Summary: Official Python SDK for Nebula API
Author-email: Nebula AI Inc <support@trynebula.ai>
License: MIT
Project-URL: Homepage, https://nebulacloud.app
Project-URL: Documentation, https://docs.nebulacloud.app
Project-URL: Repository, https://github.com/nebula-agi/nebula-sdks
Project-URL: Issues, https://github.com/nebula-agi/nebula-sdks/issues
Project-URL: Changelog, https://github.com/nebula-agi/nebula-sdks/blob/main/CHANGELOG.md
Keywords: nebula,ai,memory,vector,search,embeddings,rag
Classifier: Development Status :: 4 - Beta
Classifier: Intended Audience :: Developers
Classifier: License :: OSI Approved :: MIT License
Classifier: Programming Language :: Python :: 3
Classifier: Programming Language :: Python :: 3.10
Classifier: Programming Language :: Python :: 3.11
Classifier: Programming Language :: Python :: 3.12
Classifier: Programming Language :: Python :: 3.13
Requires-Python: >=3.10
Requires-Dist: httpx>=0.24.0
Requires-Dist: typing-extensions>=4.0.0
Requires-Dist: tiktoken>=0.6.0
Provides-Extra: dev
Requires-Dist: pytest>=7.0.0; extra == "dev"
Requires-Dist: pytest-asyncio>=0.21.0; extra == "dev"
Requires-Dist: pytest-mock>=3.10.0; extra == "dev"
Requires-Dist: ruff>=0.1.0; extra == "dev"
Requires-Dist: mypy>=1.0.0; extra == "dev"
